co2meter/__init__.py
co2meter/_version.py
co2meter/co2meter.py
co2meter/homekit.py
co2meter/server.py
co2meter/templates/dashboard.html
co2meter/templates/index.html
CO2meter-0.2.6.dist-info/LICENSE.txt
CO2meter-0.2.6.dist-info/METADATA
CO2meter-0.2.6.dist-info/WHEEL
CO2meter-0.2.6.dist-info/entry_points.txt
CO2meter-0.2.6.dist-info/top_level.txt
CO2meter-0.2.6.dist-info/RECORD
