Metadata-Version: 2.1
Name: CO2meter
Version: 0.2.6
Summary: Python interface to the USB CO2 monitor
Home-page: http://github.com/vfilimonov/co2meter
Author: Vladimir Filimonov
Author-email: vladimir.a.filimonov@gmail.com
License: MIT License
Download-URL: http://github.com/vfilimonov/co2meter/archive/v0.2.6.zip
Platform: UNKNOWN
Classifier: Programming Language :: Python :: 3
Requires-Dist: hidapi
Requires-Dist: future
